[
	{
		"time": 1554840532006,
		"file": "2019-04-09-16-08-52.zip",
		"index": 12,
		"success": true,
		"size": 1297182
	},
	{
		"time": 1554847732019,
		"file": "2019-04-09-18-08-52.zip",
		"index": 13,
		"success": true,
		"size": 1297167
	},
	{
		"time": 1554854932062,
		"file": "2019-04-09-20-08-52.zip",
		"index": 14,
		"success": true,
		"size": 1297149
	},
	{
		"time": 1554862132067,
		"file": "2019-04-09-22-08-52.zip",
		"index": 15,
		"success": true,
		"size": 1297164
	},
	{
		"time": 1554869332071,
		"file": "2019-04-10-00-08-52.zip",
		"index": 16,
		"success": true,
		"size": 1297148
	},
	{
		"time": 1554915259009,
		"file": "2019-04-10-12-54-19.zip",
		"index": 17,
		"success": true,
		"size": 1320544
	},
	{
		"time": 1554922459068,
		"file": "2019-04-10-14-54-19.zip",
		"index": 18,
		"success": true,
		"size": 1320524
	},
	{
		"time": 1554929659118,
		"file": "2019-04-10-16-54-19.zip",
		"index": 19,
		"success": true,
		"size": 1320528
	},
	{
		"time": 1554936859119,
		"file": "2019-04-10-18-54-19.zip",
		"index": 20,
		"success": true,
		"size": 1320538
	},
	{
		"time": 1554944059106,
		"file": "2019-04-10-20-54-19.zip",
		"index": 21,
		"success": true,
		"size": 1320524
	},
	{
		"time": 1554951259173,
		"file": "2019-04-10-22-54-19.zip",
		"index": 22,
		"success": true,
		"size": 1320551
	},
	{
		"time": 1554958459160,
		"file": "2019-04-11-00-54-19.zip",
		"index": 23,
		"success": true,
		"size": 1366635
	}
]