{
  "bookGuiScale": 0,
  "clickedVisualize": false,
  "bookData": {
    "pneumaticcraft:book": {
      "viewedEntries": [
        "pneumaticcraft:base_concepts/getting_started",
        "pneumaticcraft:components/compressed_iron_block",
        "pneumaticcraft:components/compressed_iron_ingot",
        "pneumaticcraft:base_concepts/heat",
        "pneumaticcraft:base_concepts/oil",
        "pneumaticcraft:base_concepts/basic_materials",
        "pneumaticcraft:base_concepts/heat_sources",
        "pneumaticcraft:base_concepts/entity_filter",
        "pneumaticcraft:base_concepts/gui",
        "pneumaticcraft:base_concepts/villagers",
        "pneumaticcraft:base_concepts/pressure",
        "pneumaticcraft:base_concepts/pressure_tiers",
        "pneumaticcraft:base_concepts/upgrades",
        "pneumaticcraft:semiblocks/crop_support",
        "pneumaticcraft:semiblocks/spawner_agitator",
        "pneumaticcraft:machines/heat_sink",
        "pneumaticcraft:tubes/pressure_tubes",
        "pneumaticcraft:components/nuke_virus",
        "pneumaticcraft:components/pcb_blueprint",
        "pneumaticcraft:components/pressure_gauge",
        "pneumaticcraft:components/stop_worm",
        "pneumaticcraft:machines/liquid_hopper",
        "pneumaticcraft:machines/omnidirectional_hopper",
        "pneumaticcraft:tools/seismic_sensor",
        "pneumaticcraft:semiblocks/heat_frame",
        "pneumaticcraft:semiblocks/transfer_gadget"
      ],
      "bookmarks": [],
      "history": [
        "pneumaticcraft:semiblocks/transfer_gadget",
        "pneumaticcraft:semiblocks/spawner_agitator",
        "pneumaticcraft:semiblocks/crop_support",
        "pneumaticcraft:semiblocks/heat_frame",
        "pneumaticcraft:tools/seismic_sensor",
        "pneumaticcraft:machines/heat_sink",
        "pneumaticcraft:machines/omnidirectional_hopper",
        "pneumaticcraft:machines/liquid_hopper",
        "pneumaticcraft:components/stop_worm",
        "pneumaticcraft:components/pressure_gauge",
        "pneumaticcraft:components/pcb_blueprint",
        "pneumaticcraft:components/nuke_virus",
        "pneumaticcraft:tubes/pressure_tubes"
      ],
      "completedManualQuests": []
    }
  }
}